nexus_keycode/__init__.py
nexus_keycode/protocols/__init__.py
nexus_keycode/protocols/channel_origin_commands.py
nexus_keycode/protocols/full.py
nexus_keycode/protocols/passthrough_uart.py
nexus_keycode/protocols/small.py
nexus_keycode/protocols/utils.py
nexus_keycode/test/__init__.py
nexus_keycode/test/protocols/__init__.py
nexus_keycode/test/protocols/test_channel_origin_commands.py
nexus_keycode/test/protocols/test_full.py
nexus_keycode/test/protocols/test_passthrough_uart.py
nexus_keycode/test/protocols/test_readme.py
nexus_keycode/test/protocols/test_small.py
nexus_keycode/test/protocols/test_utils.py
nexus_keycode-1.5.1.dist-info/LICENSE
nexus_keycode-1.5.1.dist-info/METADATA
nexus_keycode-1.5.1.dist-info/WHEEL
nexus_keycode-1.5.1.dist-info/top_level.txt
nexus_keycode-1.5.1.dist-info/RECORD
