Metadata-Version: 2.1
Name: nexus-keycode
Version: 1.5.1
Summary: Angaza Nexus backend libraries for managing PAYG devices
Home-page: https://github.com/angaza/nexus-python
Author: Angaza, Inc.
Author-email: iot@angaza.com
License: MIT
Download-URL: https://github.com/angaza/nexus-python/releases/download/1.5.1/nexus_keycode-1.5.1.tar.gz
Platform: UNKNOWN
Classifier: Development Status :: 5 - Production/Stable
Classifier: Intended Audience :: Developers
Classifier: License :: OSI Approved :: MIT License
Classifier: Operating System :: OS Independent
Classifier: Programming Language :: Python :: 2
Classifier: Programming Language :: Python :: 3
Requires-Python: >=2.7
Requires-Dist: bitstring (>=3.0.2)
Requires-Dist: enum34 (==1.1.6)
Requires-Dist: siphash (==0.0.1)
Requires-Dist: typing (>=3.7.4)
